cqzhao_test/__init__.py
cqzhao_test/cli.py
cqzhao_test-0.5.0.dist-info/WHEEL
cqzhao_test-0.5.0.dist-info/entry_points.txt
cqzhao_test-0.5.0.dist-info/METADATA
cqzhao_test-0.5.0.dist-info/RECORD
