Metadata-Version: 2.3
Name: cqzhao-test
Version: 0.5.0
Summary: A demo MCP server with weather, time, math tools
Requires-Dist: fastmcp>=0.1.0
Requires-Dist: httpx>=0.25
Requires-Dist: requests
Requires-Dist: python-dotenv
Requires-Python: >=3.8
